[
  {
    "type": "group",
    "label": {
      "en": "General",
      "nl": "Algemeen",
      "de": "Allgemein",
      "fr": "Général"
    },
    "children": [
      {
        "$extends": "status"
      }
    ]
  },
  {
    "type": "group",
    "label": {
      "en": "Information",
      "nl": "Informatie",
      "de": "Information",
      "fr": "Informations"
    },
    "children": [
      {
        "$extends": "tedee_id"
      },
      {
        "$extends": "firmware_version"
      },
      {
        "$extends": "serial_number"
      },
      {
        "$extends": "mac_address"
      }
    ]
  }
]
